{"events":[{"params":["smootherStep","In",80,-100,-1,1,false,0.04,true],"name":"customCamProperties","time":5898.87640449438},{"params":[0,"transition",true],"name":"Play Animation","time":8089.88764044944},{"params":["camGame","10","0.5"],"name":"Shake Camera","time":13483.1460674157},{"params":["camHUD","10","0.5"],"name":"Shake Camera","time":13483.1460674157},{"params":[0,"BS Bf",0],"time":29538.4615384615,"name":"Change Character"},{"params":[1],"time":30000,"name":"Camera Movement"},{"params":[1],"name":"Camera Movement","time":30000},{"params":[1],"time":30461.5384615385,"name":"Camera Movement"},{"params":[1],"name":"Camera Movement","time":30461.5384615385},{"params":[0],"time":32076.9230769231,"name":"Camera Movement"},{"params":[0],"name":"Camera Movement","time":32076.9230769231},{"params":[0],"time":33230.7692307692,"name":"Camera Movement"},{"params":[0],"name":"Camera Movement","time":33230.7692307692},{"params":[1],"time":36000,"name":"Camera Movement"},{"params":[1],"name":"Camera Movement","time":36000},{"params":[0],"time":40615.3846153846,"name":"Camera Movement"},{"params":[0],"name":"Camera Movement","time":40615.3846153846},{"params":[0],"time":42461.5384615385,"name":"Camera Movement"},{"params":[0],"name":"Camera Movement","time":42461.5384615385},{"params":[0,"crazytransition",true],"name":"Play Animation","time":44307.6923076923},{"params":[0,"CrazyBf",0],"name":"Change Character","time":44307.6923076923},{"params":[1,"scared",true],"name":"Play Animation","time":46500},{"params":[1,"Gf anim",0],"name":"Change Character","time":46500},{"params":[0],"time":48000,"name":"Camera Movement"},{"params":[0],"name":"Camera Movement","time":48000},{"params":[1],"time":49846.1538461538,"name":"Camera Movement"},{"params":[1],"name":"Camera Movement","time":49846.1538461538},{"params":[0],"time":55384.6153846154,"name":"Camera Movement"},{"params":[0],"name":"Camera Movement","time":55384.6153846154},{"params":[1],"time":59538.4615384615,"name":"Camera Movement"},{"params":[1],"name":"Camera Movement","time":59538.4615384615},{"params":[0],"time":62769.2307692308,"name":"Camera Movement"},{"params":[0],"name":"Camera Movement","time":62769.2307692308},{"params":[1],"time":66000,"name":"Camera Movement"},{"params":[1],"name":"Camera Movement","time":66000},{"params":[0],"time":68307.6923076923,"name":"Camera Movement"},{"params":[0],"name":"Camera Movement","time":68307.6923076923},{"params":[1],"time":77538.4615384615,"name":"Camera Movement"},{"params":[1],"name":"Camera Movement","time":77538.4615384615},{"params":[0],"time":84692.3076923077,"name":"Camera Movement"},{"params":[0],"name":"Camera Movement","time":84692.3076923077},{"params":[1],"time":96923.0769230769,"name":"Camera Movement"},{"params":[1],"name":"Camera Movement","time":96923.0769230769},{"params":[0],"time":106615.384615385,"name":"Camera Movement"},{"params":[0],"name":"Camera Movement","time":106615.384615385}],"strumLines":[{"notes":[{"id":1,"sLen":252.808988764045,"time":0,"type":0},{"id":3,"sLen":84.2696629213483,"time":168.539325842697,"type":0},{"id":2,"sLen":0,"time":337.078651685393,"type":0},{"id":0,"sLen":0,"time":505.61797752809,"type":0},{"id":0,"sLen":0,"time":674.157303370787,"type":0},{"id":2,"sLen":421.348314606742,"time":842.696629213483,"type":0},{"id":3,"sLen":0,"time":1348.31460674157,"type":0},{"id":3,"sLen":0,"time":1516.85393258427,"type":0},{"id":3,"sLen":0,"time":1685.39325842697,"type":0},{"id":1,"sLen":421.348314606742,"time":1853.93258426966,"type":0},{"id":2,"sLen":0,"time":2359.55056179775,"type":0},{"id":2,"sLen":0,"time":2528.08988764045,"type":0},{"id":2,"sLen":0,"time":2696.62921348315,"type":0},{"id":0,"sLen":0,"time":2865.16853932584,"type":0},{"id":0,"sLen":0,"time":3033.70786516854,"type":0},{"id":0,"sLen":0,"time":3202.24719101124,"type":0},{"id":2,"sLen":0,"time":3370.78651685393,"type":0},{"id":2,"sLen":0,"time":3539.32584269663,"type":0},{"id":2,"sLen":0,"time":3707.86516853933,"type":0},{"id":1,"sLen":421.348314606741,"time":3876.40449438202,"type":0},{"id":2,"sLen":0,"time":4382.02247191011,"type":0},{"id":1,"sLen":0,"time":4550.56179775281,"type":0},{"id":3,"sLen":0,"time":4719.10112359551,"type":0},{"id":0,"sLen":0,"time":4887.6404494382,"type":0},{"id":0,"sLen":0,"time":5056.1797752809,"type":0},{"id":0,"sLen":0,"time":5224.7191011236,"type":0},{"id":2,"sLen":0,"time":5393.25842696629,"type":0},{"id":3,"sLen":0,"time":5561.79775280899,"type":0},{"id":2,"sLen":0,"time":5730.33707865169,"type":0},{"id":0,"sLen":1601.12359550562,"time":5898.87640449438,"type":0},{"id":2,"sLen":1264.04494382022,"time":6404.49438202247,"type":0},{"id":3,"sLen":1011.23595505618,"time":6573.03370786517,"type":0},{"id":1,"sLen":1011.23595505618,"time":6741.57303370786,"type":0},{"id":0,"sLen":0,"time":13483.1460674157,"type":0},{"id":1,"sLen":0,"time":13483.1460674157,"type":0},{"id":2,"sLen":0,"time":13483.1460674157,"type":0},{"id":3,"sLen":0,"time":13483.1460674157,"type":0},{"id":0,"sLen":0,"time":13525.2808988764,"type":0},{"id":1,"sLen":0,"time":13525.2808988764,"type":0},{"id":2,"sLen":0,"time":13525.2808988764,"type":0},{"id":3,"sLen":0,"time":13525.2808988764,"type":0},{"id":0,"sLen":0,"time":13567.4157303371,"type":0},{"id":1,"sLen":0,"time":13567.4157303371,"type":0},{"id":2,"sLen":0,"time":13567.4157303371,"type":0},{"id":3,"sLen":0,"time":13567.4157303371,"type":0},{"id":0,"sLen":0,"time":13609.5505617978,"type":0},{"id":1,"sLen":0,"time":13609.5505617978,"type":0},{"id":2,"sLen":0,"time":13609.5505617978,"type":0},{"id":3,"sLen":0,"time":13609.5505617978,"type":0},{"id":0,"sLen":0,"time":13651.6853932584,"type":0},{"id":1,"sLen":0,"time":13651.6853932584,"type":0},{"id":2,"sLen":0,"time":13651.6853932584,"type":0},{"id":3,"sLen":0,"time":13651.6853932584,"type":0},{"id":0,"sLen":0,"time":13693.8202247191,"type":0},{"id":1,"sLen":0,"time":13693.8202247191,"type":0},{"id":2,"sLen":0,"time":13693.8202247191,"type":0},{"id":3,"sLen":0,"time":13693.8202247191,"type":0},{"id":0,"sLen":0,"time":13735.9550561798,"type":0},{"id":1,"sLen":0,"time":13735.9550561798,"type":0},{"id":2,"sLen":0,"time":13735.9550561798,"type":0},{"id":3,"sLen":0,"time":13735.9550561798,"type":0},{"id":0,"sLen":0,"time":13778.0898876404,"type":0},{"id":1,"sLen":0,"time":13778.0898876404,"type":0},{"id":2,"sLen":0,"time":13778.0898876404,"type":0},{"id":3,"sLen":0,"time":13778.0898876404,"type":0},{"id":0,"sLen":0,"time":13820.2247191011,"type":0},{"id":1,"sLen":0,"time":13820.2247191011,"type":0},{"id":2,"sLen":0,"time":13820.2247191011,"type":0},{"id":3,"sLen":0,"time":13820.2247191011,"type":0},{"id":0,"sLen":0,"time":13862.3595505618,"type":0},{"id":1,"sLen":0,"time":13862.3595505618,"type":0},{"id":2,"sLen":0,"time":13862.3595505618,"type":0},{"id":3,"sLen":0,"time":13862.3595505618,"type":0},{"id":0,"sLen":0,"time":13904.4943820225,"type":0},{"id":1,"sLen":0,"time":13904.4943820225,"type":0},{"id":2,"sLen":0,"time":13904.4943820225,"type":0},{"id":3,"sLen":0,"time":13904.4943820225,"type":0},{"id":0,"sLen":0,"time":13946.6292134831,"type":0},{"id":1,"sLen":0,"time":13946.6292134831,"type":0},{"id":2,"sLen":0,"time":13946.6292134831,"type":0},{"id":3,"sLen":0,"time":13946.6292134831,"type":0},{"id":0,"sLen":0,"time":13988.7640449438,"type":0},{"id":1,"sLen":0,"time":13988.7640449438,"type":0},{"id":2,"sLen":0,"time":13988.7640449438,"type":0},{"id":3,"sLen":0,"time":13988.7640449438,"type":0},{"id":0,"sLen":0,"time":14030.8988764045,"type":0},{"id":1,"sLen":0,"time":14030.8988764045,"type":0},{"id":2,"sLen":0,"time":14030.8988764045,"type":0},{"id":3,"sLen":0,"time":14030.8988764045,"type":0},{"id":0,"sLen":0,"time":14073.0337078652,"type":0},{"id":1,"sLen":0,"time":14073.0337078652,"type":0},{"id":2,"sLen":0,"time":14073.0337078652,"type":0},{"id":3,"sLen":0,"time":14073.0337078652,"type":0},{"id":0,"sLen":0,"time":14115.1685393258,"type":0},{"id":1,"sLen":0,"time":14115.1685393258,"type":0},{"id":2,"sLen":0,"time":14115.1685393258,"type":0},{"id":3,"sLen":0,"time":14115.1685393258,"type":0},{"id":0,"sLen":0,"time":14157.3033707865,"type":0},{"id":1,"sLen":0,"time":14157.3033707865,"type":0},{"id":2,"sLen":0,"time":14157.3033707865,"type":0},{"id":3,"sLen":0,"time":14157.3033707865,"type":0},{"id":0,"sLen":0,"time":14199.4382022472,"type":0},{"id":1,"sLen":0,"time":14199.4382022472,"type":0},{"id":2,"sLen":0,"time":14199.4382022472,"type":0},{"id":3,"sLen":0,"time":14199.4382022472,"type":0},{"id":0,"sLen":0,"time":14241.5730337079,"type":0},{"id":1,"sLen":0,"time":14241.5730337079,"type":0},{"id":2,"sLen":0,"time":14241.5730337079,"type":0},{"id":3,"sLen":0,"time":14241.5730337079,"type":0},{"id":0,"sLen":0,"time":14283.7078651685,"type":0},{"id":1,"sLen":0,"time":14283.7078651685,"type":0},{"id":2,"sLen":0,"time":14283.7078651685,"type":0},{"id":3,"sLen":0,"time":14283.7078651685,"type":0},{"id":0,"sLen":0,"time":14325.8426966292,"type":0},{"id":1,"sLen":0,"time":14325.8426966292,"type":0},{"id":2,"sLen":0,"time":14325.8426966292,"type":0},{"id":3,"sLen":0,"time":14325.8426966292,"type":0},{"id":0,"sLen":0,"time":14367.9775280899,"type":0},{"id":1,"sLen":0,"time":14367.9775280899,"type":0},{"id":2,"sLen":0,"time":14367.9775280899,"type":0},{"id":3,"sLen":0,"time":14367.9775280899,"type":0},{"id":0,"sLen":0,"time":14410.1123595506,"type":0},{"id":1,"sLen":0,"time":14410.1123595506,"type":0},{"id":2,"sLen":0,"time":14410.1123595506,"type":0},{"id":3,"sLen":0,"time":14410.1123595506,"type":0},{"id":0,"sLen":0,"time":14452.2471910112,"type":0},{"id":1,"sLen":0,"time":14452.2471910112,"type":0},{"id":2,"sLen":0,"time":14452.2471910112,"type":0},{"id":3,"sLen":0,"time":14452.2471910112,"type":0},{"id":0,"sLen":0,"time":14494.3820224719,"type":0},{"id":1,"sLen":0,"time":14494.3820224719,"type":0},{"id":2,"sLen":0,"time":14494.3820224719,"type":0},{"id":3,"sLen":0,"time":14494.3820224719,"type":0},{"id":0,"sLen":0,"time":14536.5168539326,"type":0},{"id":1,"sLen":0,"time":14536.5168539326,"type":0},{"id":2,"sLen":0,"time":14536.5168539326,"type":0},{"id":3,"sLen":0,"time":14536.5168539326,"type":0},{"id":0,"sLen":0,"time":14578.6516853933,"type":0},{"id":1,"sLen":0,"time":14578.6516853933,"type":0},{"id":2,"sLen":0,"time":14578.6516853933,"type":0},{"id":3,"sLen":0,"time":14578.6516853933,"type":0},{"id":0,"sLen":0,"time":14620.7865168539,"type":0},{"id":1,"sLen":0,"time":14620.7865168539,"type":0},{"id":2,"sLen":0,"time":14620.7865168539,"type":0},{"id":3,"sLen":0,"time":14620.7865168539,"type":0},{"id":0,"sLen":0,"time":14662.9213483146,"type":0},{"id":1,"sLen":0,"time":14662.9213483146,"type":0},{"id":2,"sLen":0,"time":14662.9213483146,"type":0},{"id":3,"sLen":0,"time":14662.9213483146,"type":0},{"id":0,"sLen":0,"time":14705.0561797753,"type":0},{"id":1,"sLen":0,"time":14705.0561797753,"type":0},{"id":2,"sLen":0,"time":14705.0561797753,"type":0},{"id":3,"sLen":0,"time":14705.0561797753,"type":0},{"id":0,"sLen":0,"time":14747.191011236,"type":0},{"id":1,"sLen":0,"time":14747.191011236,"type":0},{"id":2,"sLen":0,"time":14747.191011236,"type":0},{"id":3,"sLen":0,"time":14747.191011236,"type":0},{"id":0,"sLen":0,"time":14789.3258426966,"type":0},{"id":1,"sLen":0,"time":14789.3258426966,"type":0},{"id":2,"sLen":0,"time":14789.3258426966,"type":0},{"id":3,"sLen":0,"time":14789.3258426966,"type":0},{"id":0,"sLen":0,"time":14831.4606741573,"type":0},{"id":1,"sLen":0,"time":14831.4606741573,"type":0},{"id":2,"sLen":0,"time":14831.4606741573,"type":0},{"id":3,"sLen":0,"time":14831.4606741573,"type":0},{"id":0,"sLen":0,"time":14873.595505618,"type":0},{"id":1,"sLen":0,"time":14873.595505618,"type":0},{"id":2,"sLen":0,"time":14873.595505618,"type":0},{"id":3,"sLen":0,"time":14873.595505618,"type":0},{"id":0,"sLen":0,"time":14915.7303370787,"type":0},{"id":1,"sLen":0,"time":14915.7303370787,"type":0},{"id":2,"sLen":0,"time":14915.7303370787,"type":0},{"id":3,"sLen":0,"time":14915.7303370787,"type":0},{"id":0,"sLen":0,"time":14957.8651685393,"type":0},{"id":1,"sLen":0,"time":14957.8651685393,"type":0},{"id":2,"sLen":0,"time":14957.8651685393,"type":0},{"id":3,"sLen":0,"time":14957.8651685393,"type":0},{"id":0,"sLen":0,"time":15000,"type":0},{"id":1,"sLen":0,"time":15000,"type":0},{"id":2,"sLen":0,"time":15000,"type":0},{"id":3,"sLen":0,"time":15000,"type":0},{"id":0,"sLen":0,"time":15042.1348314607,"type":0},{"id":1,"sLen":0,"time":15042.1348314607,"type":0},{"id":2,"sLen":0,"time":15042.1348314607,"type":0},{"id":3,"sLen":0,"time":15042.1348314607,"type":0},{"id":0,"sLen":0,"time":15084.2696629213,"type":0},{"id":1,"sLen":0,"time":15084.2696629213,"type":0},{"id":2,"sLen":0,"time":15084.2696629213,"type":0},{"id":3,"sLen":0,"time":15084.2696629213,"type":0},{"id":0,"sLen":0,"time":15126.404494382,"type":0},{"id":1,"sLen":0,"time":15126.404494382,"type":0},{"id":2,"sLen":0,"time":15126.404494382,"type":0},{"id":3,"sLen":0,"time":15126.404494382,"type":0},{"id":0,"sLen":0,"time":15168.5393258427,"type":0},{"id":1,"sLen":0,"time":15168.5393258427,"type":0},{"id":2,"sLen":0,"time":15168.5393258427,"type":0},{"id":3,"sLen":0,"time":15168.5393258427,"type":0},{"id":0,"sLen":0,"time":15210.6741573034,"type":0},{"id":1,"sLen":0,"time":15210.6741573034,"type":0},{"id":2,"sLen":0,"time":15210.6741573034,"type":0},{"id":3,"sLen":0,"time":15210.6741573034,"type":0},{"id":0,"sLen":0,"time":15252.808988764,"type":0},{"id":1,"sLen":0,"time":15252.808988764,"type":0},{"id":2,"sLen":0,"time":15252.808988764,"type":0},{"id":3,"sLen":0,"time":15252.808988764,"type":0},{"id":0,"sLen":0,"time":15294.9438202247,"type":0},{"id":1,"sLen":0,"time":15294.9438202247,"type":0},{"id":2,"sLen":0,"time":15294.9438202247,"type":0},{"id":3,"sLen":0,"time":15294.9438202247,"type":0},{"id":0,"sLen":0,"time":15337.0786516854,"type":0},{"id":1,"sLen":0,"time":15337.0786516854,"type":0},{"id":2,"sLen":0,"time":15337.0786516854,"type":0},{"id":3,"sLen":0,"time":15337.0786516854,"type":0},{"id":0,"sLen":0,"time":15379.2134831461,"type":0},{"id":1,"sLen":0,"time":15379.2134831461,"type":0},{"id":2,"sLen":0,"time":15379.2134831461,"type":0},{"id":3,"sLen":0,"time":15379.2134831461,"type":0},{"id":0,"sLen":0,"time":15421.3483146067,"type":0},{"id":1,"sLen":0,"time":15421.3483146067,"type":0},{"id":2,"sLen":0,"time":15421.3483146067,"type":0},{"id":3,"sLen":0,"time":15421.3483146067,"type":0},{"id":0,"sLen":0,"time":15463.4831460674,"type":0},{"id":1,"sLen":0,"time":15463.4831460674,"type":0},{"id":2,"sLen":0,"time":15463.4831460674,"type":0},{"id":3,"sLen":0,"time":15463.4831460674,"type":0},{"id":0,"sLen":0,"time":15505.6179775281,"type":0},{"id":1,"sLen":0,"time":15505.6179775281,"type":0},{"id":2,"sLen":0,"time":15505.6179775281,"type":0},{"id":3,"sLen":0,"time":15505.6179775281,"type":0},{"id":0,"sLen":0,"time":15547.7528089888,"type":0},{"id":1,"sLen":0,"time":15547.7528089888,"type":0},{"id":2,"sLen":0,"time":15547.7528089888,"type":0},{"id":3,"sLen":0,"time":15547.7528089888,"type":0},{"id":0,"sLen":0,"time":15589.8876404494,"type":0},{"id":1,"sLen":0,"time":15589.8876404494,"type":0},{"id":2,"sLen":0,"time":15589.8876404494,"type":0},{"id":3,"sLen":0,"time":15589.8876404494,"type":0},{"id":0,"sLen":0,"time":15632.0224719101,"type":0},{"id":1,"sLen":0,"time":15632.0224719101,"type":0},{"id":2,"sLen":0,"time":15632.0224719101,"type":0},{"id":3,"sLen":0,"time":15632.0224719101,"type":0},{"id":0,"sLen":0,"time":15674.1573033708,"type":0},{"id":1,"sLen":0,"time":15674.1573033708,"type":0},{"id":2,"sLen":0,"time":15674.1573033708,"type":0},{"id":3,"sLen":0,"time":15674.1573033708,"type":0},{"id":0,"sLen":0,"time":15716.2921348315,"type":0},{"id":1,"sLen":0,"time":15716.2921348315,"type":0},{"id":2,"sLen":0,"time":15716.2921348315,"type":0},{"id":3,"sLen":0,"time":15716.2921348315,"type":0},{"id":0,"sLen":0,"time":15758.4269662921,"type":0},{"id":1,"sLen":0,"time":15758.4269662921,"type":0},{"id":2,"sLen":0,"time":15758.4269662921,"type":0},{"id":3,"sLen":0,"time":15758.4269662921,"type":0},{"id":0,"sLen":0,"time":15800.5617977528,"type":0},{"id":1,"sLen":0,"time":15800.5617977528,"type":0},{"id":2,"sLen":0,"time":15800.5617977528,"type":0},{"id":3,"sLen":0,"time":15800.5617977528,"type":0},{"id":0,"sLen":0,"time":15842.6966292135,"type":0},{"id":1,"sLen":0,"time":15842.6966292135,"type":0},{"id":2,"sLen":0,"time":15842.6966292135,"type":0},{"id":3,"sLen":0,"time":15842.6966292135,"type":0},{"id":0,"sLen":0,"time":15884.8314606742,"type":0},{"id":1,"sLen":0,"time":15884.8314606742,"type":0},{"id":2,"sLen":0,"time":15884.8314606742,"type":0},{"id":3,"sLen":0,"time":15884.8314606742,"type":0}],"position":"dad","strumScale":1,"visible":true,"type":0,"characters":["Freaky Bidi"],"strumPos":[0,50],"strumLinePos":0.75,"vocalsSuffix":""}],"stage":"freaky","scrollSpeed":3,"codenameChart":true,"noteTypes":[]}